NoiseX/__init__.py
NoiseX/perlin_noise.py
NoiseX/perlin_worms.py
NoiseX/simplex_noise.py
NoiseX-0.0.4.dist-info/LICENSE
NoiseX-0.0.4.dist-info/METADATA
NoiseX-0.0.4.dist-info/WHEEL
NoiseX-0.0.4.dist-info/top_level.txt
NoiseX-0.0.4.dist-info/RECORD
