Metadata-Version: 2.1
Name: NoiseX
Version: 0.0.4
Summary: A python package for perlin noise, simplex noise and perlin worms.
Home-page: https://github.com/somePythonProgrammer/NoiseX
Author: somePythonProgrammer
Author-email: leenagajbhiye1003@gmail.com
License: MIT
Download-URL: https://pypi.org/project/NoiseX/
Keywords: Noise,Perlin,Worms,Simplex
Platform: UNKNOWN
License-File: LICENSE
Requires-Dist: vnoise
Requires-Dist: opensimplex
